{
    "batch_get_aggregate_resource_config": {
        "ConfigurationAggregatorName": {
            "Description": "The name of the configuration aggregator.",
            "Type": "string",
            "Required": true
        },
        "ResourceIdentifiers": {
            "Description": "A list of aggregate ResourceIdentifiers objects.",
            "Type": "list",
            "Required": true,
            "list variables": {}
        }
    },
    "batch_get_resource_config": {
        "resourceKeys": {
            "Description": "A list of resource keys to be processed with the current request. Each element in the list consists of the resource type and resource ID.",
            "Type": "list",
            "Required": true,
            "list variables": {}
        }
    },
    "delete_aggregation_authorization": {
        "AuthorizedAccountId": {
            "Description": "The 12-digit account ID of the account authorized to aggregate data.",
            "Type": "string",
            "Required": true
        },
        "AuthorizedAwsRegion": {
            "Description": "The region authorized to collect aggregated data.",
            "Type": "string",
            "Required": true
        }
    },
    "delete_config_rule": {
        "ConfigRuleName": {
            "Description": "The name of the Config rule that you want to delete.",
            "Type": "string",
            "Required": true
        }
    },
    "delete_configuration_aggregator": {
        "ConfigurationAggregatorName": {
            "Description": "The name of the configuration aggregator.",
            "Type": "string",
            "Required": true
        }
    },
    "delete_configuration_recorder": {
        "ConfigurationRecorderName": {
            "Description": "The name of the configuration recorder to be deleted. You can retrieve the name of your configuration recorder by using the DescribeConfigurationRecorders action.",
            "Type": "string",
            "Required": true
        }
    },
    "delete_conformance_pack": {
        "ConformancePackName": {
            "Description": "Name of the conformance pack you want to delete.",
            "Type": "string",
            "Required": true
        }
    },
    "delete_delivery_channel": {
        "DeliveryChannelName": {
            "Description": "The name of the delivery channel to delete.",
            "Type": "string",
            "Required": true
        }
    },
    "delete_evaluation_results": {
        "ConfigRuleName": {
            "Description": "The name of the Config rule for which you want to delete the evaluation results.",
            "Type": "string",
            "Required": true
        }
    },
    "delete_organization_config_rule": {
        "OrganizationConfigRuleName": {
            "Description": "The name of organization Config rule that you want to delete.",
            "Type": "string",
            "Required": true
        }
    },
    "delete_organization_conformance_pack": {
        "OrganizationConformancePackName": {
            "Description": "The name of organization conformance pack that you want to delete.",
            "Type": "string",
            "Required": true
        }
    },
    "delete_pending_aggregation_request": {
        "RequesterAccountId": {
            "Description": "The 12-digit account ID of the account requesting to aggregate data.",
            "Type": "string",
            "Required": true
        },
        "RequesterAwsRegion": {
            "Description": "The region requesting to aggregate data.",
            "Type": "string",
            "Required": true
        }
    },
    "delete_remediation_configuration": {
        "ConfigRuleName": {
            "Description": "The name of the Config rule for which you want to delete remediation configuration.",
            "Type": "string",
            "Required": true
        },
        "ResourceType": {
            "Description": "The type of a resource.",
            "Type": "string",
            "Required": false
        }
    },
    "delete_remediation_exceptions": {
        "ConfigRuleName": {
            "Description": "The name of the Config rule for which you want to delete remediation exception configuration.",
            "Type": "string",
            "Required": true
        },
        "ResourceKeys": {
            "Description": "An exception list of resource exception keys to be processed with the current request. Config adds exception for each resource key. For example, Config adds 3 exceptions for 3 resource keys.",
            "Type": "list",
            "Required": true,
            "list variables": {}
        }
    },
    "delete_resource_config": {
        "ResourceType": {
            "Description": "The type of the resource.",
            "Type": "string",
            "Required": true
        },
        "ResourceId": {
            "Description": "Unique identifier of the resource.",
            "Type": "string",
            "Required": true
        }
    },
    "delete_retention_configuration": {
        "RetentionConfigurationName": {
            "Description": "The name of the retention configuration to delete.",
            "Type": "string",
            "Required": true
        }
    },
    "delete_stored_query": {
        "QueryName": {
            "Description": "The name of the query that you want to delete.",
            "Type": "string",
            "Required": true
        }
    },
    "deliver_config_snapshot": {
        "deliveryChannelName": {
            "Description": "The name of the delivery channel through which the snapshot is delivered.",
            "Type": "string",
            "Required": true
        }
    },
    "describe_aggregate_compliance_by_config_rules": {
        "ConfigurationAggregatorName": {
            "Description": "The name of the configuration aggregator.",
            "Type": "string",
            "Required": true
        },
        "Filters": {
            "Description": "Filters the results by ConfigRuleComplianceFilters object.",
            "Type": "dict",
            "Required": false,
            "dict variables": {}
        },
        "Limit": {
            "Description": "The maximum number of evaluation results returned on each page. The default is maximum. If you specify 0, Config uses the default.",
            "Type": "integer",
            "Required": false
        },
        "NextToken": {
            "Description": "The nextToken string returned on a previous page that you use to get the next page of results in a paginated response.",
            "Type": "string",
            "Required": false
        }
    },
    "describe_aggregate_compliance_by_conformance_packs": {
        "ConfigurationAggregatorName": {
            "Description": "The name of the configuration aggregator.",
            "Type": "string",
            "Required": true
        },
        "Filters": {
            "Description": "Filters the result by AggregateConformancePackComplianceFilters object.",
            "Type": "dict",
            "Required": false,
            "dict variables": {}
        },
        "Limit": {
            "Description": "The maximum number of conformance packs compliance details returned on each page. The default is maximum. If you specify 0, Config uses the default.",
            "Type": "integer",
            "Required": false
        },
        "NextToken": {
            "Description": "The nextToken string returned on a previous page that you use to get the next page of results in a paginated response.",
            "Type": "string",
            "Required": false
        }
    },
    "describe_aggregation_authorizations": {
        "Limit": {
            "Description": "The maximum number of AggregationAuthorizations returned on each page. The default is maximum. If you specify 0, Config uses the default.",
            "Type": "integer",
            "Required": false
        },
        "NextToken": {
            "Description": "The nextToken string returned on a previous page that you use to get the next page of results in a paginated response.",
            "Type": "string",
            "Required": false
        }
    },
    "describe_compliance_by_config_rule": {
        "ConfigRuleNames": {
            "Description": "Specify one or more Config rule names to filter the results by rule.",
            "Type": "list",
            "Required": false,
            "list variables": {}
        },
        "ComplianceTypes": {
            "Description": "Filters the results by compliance.\nThe allowed values are COMPLIANT and NON_COMPLIANT .",
            "Type": "list",
            "Required": false,
            "list variables": {}
        },
        "NextToken": {
            "Description": "The nextToken string returned on a previous page that you use to get the next page of results in a paginated response.",
            "Type": "string",
            "Required": false
        }
    },
    "describe_compliance_by_resource": {
        "ResourceType": {
            "Description": "The types of Amazon Web Services resources for which you want compliance information (for example, AWS::EC2::Instance ). For this action, you can specify that the resource type is an Amazon Web Services account by specifying AWS::::Account .",
            "Type": "string",
            "Required": false
        },
        "ResourceId": {
            "Description": "The ID of the Amazon Web Services resource for which you want compliance information. You can specify only one resource ID. If you specify a resource ID, you must also specify a type for ResourceType .",
            "Type": "string",
            "Required": false
        },
        "ComplianceTypes": {
            "Description": "Filters the results by compliance.\nThe allowed values are COMPLIANT, NON_COMPLIANT, and INSUFFICIENT_DATA .",
            "Type": "list",
            "Required": false,
            "list variables": {}
        },
        "Limit": {
            "Description": "The maximum number of evaluation results returned on each page. The default is 10. You cannot specify a number greater than 100. If you specify 0, Config uses the default.",
            "Type": "integer",
            "Required": false
        },
        "NextToken": {
            "Description": "The nextToken string returned on a previous page that you use to get the next page of results in a paginated response.",
            "Type": "string",
            "Required": false
        }
    },
    "describe_config_rule_evaluation_status": {
        "ConfigRuleNames": {
            "Description": "The name of the Config managed rules for which you want status information. If you do not specify any names, Config returns status information for all Config managed rules that you use.",
            "Type": "list",
            "Required": false,
            "list variables": {}
        },
        "NextToken": {
            "Description": "The nextToken string returned on a previous page that you use to get the next page of results in a paginated response.",
            "Type": "string",
            "Required": false
        },
        "Limit": {
            "Description": "The number of rule evaluation results that you want returned.\nThis parameter is required if the rule limit for your account is more than the default of 150 rules.\nFor information about requesting a rule limit increase, see Config Limits in the Amazon Web Services General Reference Guide .",
            "Type": "integer",
            "Required": false
        }
    },
    "describe_config_rules": {
        "ConfigRuleNames": {
            "Description": "The names of the Config rules for which you want details. If you do not specify any names, Config returns details for all your rules.",
            "Type": "list",
            "Required": false,
            "list variables": {}
        },
        "NextToken": {
            "Description": "The nextToken string returned on a previous page that you use to get the next page of results in a paginated response.",
            "Type": "string",
            "Required": false
        }
    },
    "describe_configuration_aggregator_sources_status": {
        "ConfigurationAggregatorName": {
            "Description": "The name of the configuration aggregator.",
            "Type": "string",
            "Required": true
        },
        "UpdateStatus": {
            "Description": "Filters the status type.",
            "Type": "list",
            "Required": false,
            "list variables": [
                {},
                {}
            ]
        },
        "NextToken": {
            "Description": "The nextToken string returned on a previous page that you use to get the next page of results in a paginated response.",
            "Type": "string",
            "Required": false
        },
        "Limit": {
            "Description": "The maximum number of AggregatorSourceStatus returned on each page. The default is maximum. If you specify 0, Config uses the default.",
            "Type": "integer",
            "Required": false
        }
    },
    "describe_configuration_aggregators": {
        "ConfigurationAggregatorNames": {
            "Description": "The name of the configuration aggregators.",
            "Type": "list",
            "Required": false,
            "list variables": {}
        },
        "NextToken": {
            "Description": "The nextToken string returned on a previous page that you use to get the next page of results in a paginated response.",
            "Type": "string",
            "Required": false
        },
        "Limit": {
            "Description": "The maximum number of configuration aggregators returned on each page. The default is maximum. If you specify 0, Config uses the default.",
            "Type": "integer",
            "Required": false
        }
    },
    "describe_configuration_recorder_status": {
        "ConfigurationRecorderNames": {
            "Description": "The name(s) of the configuration recorder. If the name is not specified, the action returns the current status of all the configuration recorders associated with the account.",
            "Type": "list",
            "Required": false,
            "list variables": {}
        }
    },
    "describe_configuration_recorders": {
        "ConfigurationRecorderNames": {
            "Description": "A list of configuration recorder names.",
            "Type": "list",
            "Required": false,
            "list variables": {}
        }
    },
    "describe_conformance_pack_compliance": {
        "ConformancePackName": {
            "Description": "Name of the conformance pack.",
            "Type": "string",
            "Required": true
        },
        "Filters": {
            "Description": "A ConformancePackComplianceFilters object.",
            "Type": "dict",
            "Required": false,
            "dict variables": {}
        },
        "Limit": {
            "Description": "The maximum number of Config rules within a conformance pack are returned on each page.",
            "Type": "integer",
            "Required": false
        },
        "NextToken": {
            "Description": "The nextToken string returned in a previous request that you use to request the next page of results in a paginated response.",
            "Type": "string",
            "Required": false
        }
    },
    "describe_conformance_pack_status": {
        "ConformancePackNames": {
            "Description": "Comma-separated list of conformance pack names.",
            "Type": "list",
            "Required": false,
            "list variables": {}
        },
        "Limit": {
            "Description": "The maximum number of conformance packs status returned on each page.",
            "Type": "integer",
            "Required": false
        },
        "NextToken": {
            "Description": "The nextToken string returned in a previous request that you use to request the next page of results in a paginated response.",
            "Type": "string",
            "Required": false
        }
    },
    "describe_conformance_packs": {
        "ConformancePackNames": {
            "Description": "Comma-separated list of conformance pack names for which you want details. If you do not specify any names, Config returns details for all your conformance packs.",
            "Type": "list",
            "Required": false,
            "list variables": {}
        },
        "Limit": {
            "Description": "The maximum number of conformance packs returned on each page.",
            "Type": "integer",
            "Required": false
        },
        "NextToken": {
            "Description": "The nextToken string returned in a previous request that you use to request the next page of results in a paginated response.",
            "Type": "string",
            "Required": false
        }
    },
    "describe_delivery_channel_status": {
        "DeliveryChannelNames": {
            "Description": "A list of delivery channel names.",
            "Type": "list",
            "Required": false,
            "list variables": {}
        }
    },
    "describe_delivery_channels": {
        "DeliveryChannelNames": {
            "Description": "A list of delivery channel names.",
            "Type": "list",
            "Required": false,
            "list variables": {}
        }
    },
    "describe_organization_config_rule_statuses": {
        "OrganizationConfigRuleNames": {
            "Description": "The names of organization Config rules for which you want status details. If you do not specify any names, Config returns details for all your organization Config rules.",
            "Type": "list",
            "Required": false,
            "list variables": {}
        },
        "Limit": {
            "Description": "The maximum number of OrganizationConfigRuleStatuses returned on each page. If you do no specify a number, Config uses the default. The default is 100.",
            "Type": "integer",
            "Required": false
        },
        "NextToken": {
            "Description": "The nextToken string returned on a previous page that you use to get the next page of results in a paginated response.",
            "Type": "string",
            "Required": false
        }
    },
    "describe_organization_config_rules": {
        "OrganizationConfigRuleNames": {
            "Description": "The names of organization Config rules for which you want details. If you do not specify any names, Config returns details for all your organization Config rules.",
            "Type": "list",
            "Required": false,
            "list variables": {}
        },
        "Limit": {
            "Description": "The maximum number of organization Config rules returned on each page. If you do no specify a number, Config uses the default. The default is 100.",
            "Type": "integer",
            "Required": false
        },
        "NextToken": {
            "Description": "The nextToken string returned on a previous page that you use to get the next page of results in a paginated response.",
            "Type": "string",
            "Required": false
        }
    },
    "describe_organization_conformance_pack_statuses": {
        "OrganizationConformancePackNames": {
            "Description": "The names of organization conformance packs for which you want status details. If you do not specify any names, Config returns details for all your organization conformance packs.",
            "Type": "list",
            "Required": false,
            "list variables": {}
        },
        "Limit": {
            "Description": "The maximum number of OrganizationConformancePackStatuses returned on each page. If you do no specify a number, Config uses the default. The default is 100.",
            "Type": "integer",
            "Required": false
        },
        "NextToken": {
            "Description": "The nextToken string returned on a previous page that you use to get the next page of results in a paginated response.",
            "Type": "string",
            "Required": false
        }
    },
    "describe_organization_conformance_packs": {
        "OrganizationConformancePackNames": {
            "Description": "The name that you assign to an organization conformance pack.",
            "Type": "list",
            "Required": false,
            "list variables": {}
        },
        "Limit": {
            "Description": "The maximum number of organization config packs returned on each page. If you do no specify a number, Config uses the default. The default is 100.",
            "Type": "integer",
            "Required": false
        },
        "NextToken": {
            "Description": "The nextToken string returned on a previous page that you use to get the next page of results in a paginated response.",
            "Type": "string",
            "Required": false
        }
    },
    "describe_pending_aggregation_requests": {
        "Limit": {
            "Description": "The maximum number of evaluation results returned on each page. The default is maximum. If you specify 0, Config uses the default.",
            "Type": "integer",
            "Required": false
        },
        "NextToken": {
            "Description": "The nextToken string returned on a previous page that you use to get the next page of results in a paginated response.",
            "Type": "string",
            "Required": false
        }
    },
    "describe_remediation_configurations": {
        "ConfigRuleNames": {
            "Description": "A list of Config rule names of remediation configurations for which you want details.",
            "Type": "list",
            "Required": true,
            "list variables": {}
        }
    },
    "describe_remediation_exceptions": {
        "ConfigRuleName": {
            "Description": "The name of the Config rule.",
            "Type": "string",
            "Required": true
        },
        "ResourceKeys": {
            "Description": "An exception list of resource exception keys to be processed with the current request. Config adds exception for each resource key. For example, Config adds 3 exceptions for 3 resource keys.",
            "Type": "list",
            "Required": false,
            "list variables": {}
        },
        "Limit": {
            "Description": "The maximum number of RemediationExceptionResourceKey returned on each page. The default is 25. If you specify 0, Config uses the default.",
            "Type": "integer",
            "Required": false
        },
        "NextToken": {
            "Description": "The nextToken string returned in a previous request that you use to request the next page of results in a paginated response.",
            "Type": "string",
            "Required": false
        }
    },
    "describe_remediation_execution_status": {
        "ConfigRuleName": {
            "Description": "A list of Config rule names.",
            "Type": "string",
            "Required": true
        },
        "ResourceKeys": {
            "Description": "A list of resource keys to be processed with the current request. Each element in the list consists of the resource type and resource ID.",
            "Type": "list",
            "Required": false,
            "list variables": {}
        },
        "Limit": {
            "Description": "The maximum number of RemediationExecutionStatuses returned on each page. The default is maximum. If you specify 0, Config uses the default.",
            "Type": "integer",
            "Required": false
        },
        "NextToken": {
            "Description": "The nextToken string returned on a previous page that you use to get the next page of results in a paginated response.",
            "Type": "string",
            "Required": false
        }
    },
    "describe_retention_configurations": {
        "RetentionConfigurationNames": {
            "Description": "A list of names of retention configurations for which you want details. If you do not specify a name, Config returns details for all the retention configurations for that account.",
            "Type": "list",
            "Required": false,
            "list variables": {}
        },
        "NextToken": {
            "Description": "The nextToken string returned on a previous page that you use to get the next page of results in a paginated response.",
            "Type": "string",
            "Required": false
        }
    },
    "get_aggregate_compliance_details_by_config_rule": {
        "ConfigurationAggregatorName": {
            "Description": "The name of the configuration aggregator.",
            "Type": "string",
            "Required": true
        },
        "ConfigRuleName": {
            "Description": "The name of the Config rule for which you want compliance information.",
            "Type": "string",
            "Required": true
        },
        "AccountId": {
            "Description": "The 12-digit account ID of the source account.",
            "Type": "string",
            "Required": true
        },
        "AwsRegion": {
            "Description": "The source region from where the data is aggregated.",
            "Type": "string",
            "Required": true
        },
        "ComplianceType": {
            "Description": "The resource compliance status.",
            "Type": "string",
            "Required": false
        },
        "Limit": {
            "Description": "The maximum number of evaluation results returned on each page. The default is 50. You cannot specify a number greater than 100. If you specify 0, Config uses the default.",
            "Type": "integer",
            "Required": false
        },
        "NextToken": {
            "Description": "The nextToken string returned on a previous page that you use to get the next page of results in a paginated response.",
            "Type": "string",
            "Required": false
        }
    },
    "get_aggregate_config_rule_compliance_summary": {
        "ConfigurationAggregatorName": {
            "Description": "The name of the configuration aggregator.",
            "Type": "string",
            "Required": true
        },
        "Filters": {
            "Description": "Filters the results based on the ConfigRuleComplianceSummaryFilters object.",
            "Type": "dict",
            "Required": false,
            "dict variables": {}
        },
        "GroupByKey": {
            "Description": "Groups the result based on ACCOUNT_ID or AWS_REGION.",
            "Type": "string",
            "Required": false
        },
        "Limit": {
            "Description": "The maximum number of evaluation results returned on each page. The default is 1000. You cannot specify a number greater than 1000. If you specify 0, Config uses the default.",
            "Type": "integer",
            "Required": false
        },
        "NextToken": {
            "Description": "The nextToken string returned on a previous page that you use to get the next page of results in a paginated response.",
            "Type": "string",
            "Required": false
        }
    },
    "get_aggregate_conformance_pack_compliance_summary": {
        "ConfigurationAggregatorName": {
            "Description": "The name of the configuration aggregator.",
            "Type": "string",
            "Required": true
        },
        "Filters": {
            "Description": "Filters the results based on the AggregateConformancePackComplianceSummaryFilters object.",
            "Type": "dict",
            "Required": false,
            "dict variables": {}
        },
        "GroupByKey": {
            "Description": "Groups the result based on Amazon Web Services account ID or Amazon Web Services Region.",
            "Type": "string",
            "Required": false
        },
        "Limit": {
            "Description": "The maximum number of results returned on each page. The default is maximum. If you specify 0, Config uses the default.",
            "Type": "integer",
            "Required": false
        },
        "NextToken": {
            "Description": "The nextToken string returned on a previous page that you use to get the next page of results in a paginated response.",
            "Type": "string",
            "Required": false
        }
    },
    "get_aggregate_discovered_resource_counts": {
        "ConfigurationAggregatorName": {
            "Description": "The name of the configuration aggregator.",
            "Type": "string",
            "Required": true
        },
        "Filters": {
            "Description": "Filters the results based on the ResourceCountFilters object.",
            "Type": "dict",
            "Required": false,
            "dict variables": {}
        },
        "GroupByKey": {
            "Description": "The key to group the resource counts.",
            "Type": "string",
            "Required": false
        },
        "Limit": {
            "Description": "The maximum number of  GroupedResourceCount objects returned on each page. The default is 1000. You cannot specify a number greater than 1000. If you specify 0, Config uses the default.",
            "Type": "integer",
            "Required": false
        },
        "NextToken": {
            "Description": "The nextToken string returned on a previous page that you use to get the next page of results in a paginated response.",
            "Type": "string",
            "Required": false
        }
    },
    "get_aggregate_resource_config": {
        "ConfigurationAggregatorName": {
            "Description": "The name of the configuration aggregator.",
            "Type": "string",
            "Required": true
        },
        "ResourceIdentifier": {
            "Description": "An object that identifies aggregate resource.",
            "Type": "dict",
            "Required": true,
            "dict variables": {}
        }
    },
    "get_compliance_details_by_config_rule": {
        "ConfigRuleName": {
            "Description": "The name of the Config rule for which you want compliance information.",
            "Type": "string",
            "Required": true
        },
        "ComplianceTypes": {
            "Description": "Filters the results by compliance.\nThe allowed values are COMPLIANT, NON_COMPLIANT, and NOT_APPLICABLE .",
            "Type": "list",
            "Required": false,
            "list variables": {}
        },
        "Limit": {
            "Description": "The maximum number of evaluation results returned on each page. The default is 10. You cannot specify a number greater than 100. If you specify 0, Config uses the default.",
            "Type": "integer",
            "Required": false
        },
        "NextToken": {
            "Description": "The nextToken string returned on a previous page that you use to get the next page of results in a paginated response.",
            "Type": "string",
            "Required": false
        }
    },
    "get_compliance_details_by_resource": {
        "ResourceType": {
            "Description": "The type of the Amazon Web Services resource for which you want compliance information.",
            "Type": "string",
            "Required": true
        },
        "ResourceId": {
            "Description": "The ID of the Amazon Web Services resource for which you want compliance information.",
            "Type": "string",
            "Required": true
        },
        "ComplianceTypes": {
            "Description": "Filters the results by compliance.\nThe allowed values are COMPLIANT, NON_COMPLIANT, and NOT_APPLICABLE .",
            "Type": "list",
            "Required": false,
            "list variables": {}
        },
        "NextToken": {
            "Description": "The nextToken string returned on a previous page that you use to get the next page of results in a paginated response.",
            "Type": "string",
            "Required": false
        }
    },
    "get_compliance_summary_by_config_rule": "No parameters defined",
    "get_compliance_summary_by_resource_type": {
        "ResourceTypes": {
            "Description": "Specify one or more resource types to get the number of resources that are compliant and the number that are noncompliant for each resource type.\nFor this request, you can specify an Amazon Web Services resource type such as AWS::EC2::Instance. You can specify that the resource type is an Amazon Web Services account by specifying AWS::::Account .",
            "Type": "list",
            "Required": false,
            "list variables": {}
        }
    },
    "get_conformance_pack_compliance_details": {
        "ConformancePackName": {
            "Description": "Name of the conformance pack.",
            "Type": "string",
            "Required": true
        },
        "Filters": {
            "Description": "A ConformancePackEvaluationFilters object.",
            "Type": "dict",
            "Required": false,
            "dict variables": {}
        },
        "Limit": {
            "Description": "The maximum number of evaluation results returned on each page. If you do no specify a number, Config uses the default. The default is 100.",
            "Type": "integer",
            "Required": false
        },
        "NextToken": {
            "Description": "The nextToken string returned in a previous request that you use to request the next page of results in a paginated response.",
            "Type": "string",
            "Required": false
        }
    },
    "get_conformance_pack_compliance_summary": {
        "ConformancePackNames": {
            "Description": "Names of conformance packs.",
            "Type": "list",
            "Required": true,
            "list variables": {}
        },
        "Limit": {
            "Description": "The maximum number of conformance packs returned on each page.",
            "Type": "integer",
            "Required": false
        },
        "NextToken": {
            "Description": "The nextToken string returned on a previous page that you use to get the next page of results in a paginated response.",
            "Type": "string",
            "Required": false
        }
    },
    "get_custom_rule_policy": {
        "ConfigRuleName": {
            "Description": "The name of your Config Custom Policy rule.",
            "Type": "string",
            "Required": false
        }
    },
    "get_discovered_resource_counts": {
        "resourceTypes": {
            "Description": "The comma-separated list that specifies the resource types that you want Config to return (for example, \"AWS::EC2::Instance\", \"AWS::IAM::User\" ).\nIf a value for resourceTypes is not specified, Config returns all resource types that Config is recording in the region for your account.",
            "Type": "list",
            "Required": false,
            "list variables": {}
        },
        "limit": {
            "Description": "The maximum number of  ResourceCount objects returned on each page. The default is 100. You cannot specify a number greater than 100. If you specify 0, Config uses the default.",
            "Type": "integer",
            "Required": false
        },
        "nextToken": {
            "Description": "The nextToken string returned on a previous page that you use to get the next page of results in a paginated response.",
            "Type": "string",
            "Required": false
        }
    },
    "get_organization_config_rule_detailed_status": {
        "OrganizationConfigRuleName": {
            "Description": "The name of your organization Config rule for which you want status details for member accounts.",
            "Type": "string",
            "Required": true
        },
        "Filters": {
            "Description": "A StatusDetailFilters object.",
            "Type": "dict",
            "Required": false,
            "dict variables": {}
        },
        "Limit": {
            "Description": "The maximum number of OrganizationConfigRuleDetailedStatus returned on each page. If you do not specify a number, Config uses the default. The default is 100.",
            "Type": "integer",
            "Required": false
        },
        "NextToken": {
            "Description": "The nextToken string returned on a previous page that you use to get the next page of results in a paginated response.",
            "Type": "string",
            "Required": false
        }
    },
    "get_organization_conformance_pack_detailed_status": {
        "OrganizationConformancePackName": {
            "Description": "The name of organization conformance pack for which you want status details for member accounts.",
            "Type": "string",
            "Required": true
        },
        "Filters": {
            "Description": "An OrganizationResourceDetailedStatusFilters object.",
            "Type": "dict",
            "Required": false,
            "dict variables": {}
        },
        "Limit": {
            "Description": "The maximum number of OrganizationConformancePackDetailedStatuses returned on each page. If you do not specify a number, Config uses the default. The default is 100.",
            "Type": "integer",
            "Required": false
        },
        "NextToken": {
            "Description": "The nextToken string returned on a previous page that you use to get the next page of results in a paginated response.",
            "Type": "string",
            "Required": false
        }
    },
    "get_organization_custom_rule_policy": {
        "OrganizationConfigRuleName": {
            "Description": "The name of your organization Config Custom Policy rule.",
            "Type": "string",
            "Required": true
        }
    },
    "get_resource_config_history": {
        "resourceType": {
            "Description": "The resource type.",
            "Type": "string",
            "Required": true
        },
        "resourceId": {
            "Description": "The ID of the resource (for example., sg-xxxxxx ).",
            "Type": "string",
            "Required": true
        },
        "laterTime": {
            "Description": "The time stamp that indicates a later time. If not specified, current time is taken.",
            "Type": "datetime",
            "Required": false
        },
        "earlierTime": {
            "Description": "The time stamp that indicates an earlier time. If not specified, the action returns paginated results that contain configuration items that start when the first configuration item was recorded.",
            "Type": "datetime",
            "Required": false
        },
        "chronologicalOrder": {
            "Description": "The chronological order for configuration items listed. By default, the results are listed in reverse chronological order.",
            "Type": "string",
            "Required": false
        },
        "limit": {
            "Description": "The maximum number of configuration items returned on each page. The default is 10. You cannot specify a number greater than 100. If you specify 0, Config uses the default.",
            "Type": "integer",
            "Required": false
        },
        "nextToken": {
            "Description": "The nextToken string returned on a previous page that you use to get the next page of results in a paginated response.",
            "Type": "string",
            "Required": false
        }
    },
    "get_stored_query": {
        "QueryName": {
            "Description": "The name of the query.",
            "Type": "string",
            "Required": true
        }
    },
    "list_aggregate_discovered_resources": {
        "ConfigurationAggregatorName": {
            "Description": "The name of the configuration aggregator.",
            "Type": "string",
            "Required": true
        },
        "ResourceType": {
            "Description": "The type of resources that you want Config to list in the response.",
            "Type": "string",
            "Required": true
        },
        "Filters": {
            "Description": "Filters the results based on the ResourceFilters object.",
            "Type": "dict",
            "Required": false,
            "dict variables": {}
        },
        "Limit": {
            "Description": "The maximum number of resource identifiers returned on each page. You cannot specify a number greater than 100. If you specify 0, Config uses the default.",
            "Type": "integer",
            "Required": false
        },
        "NextToken": {
            "Description": "The nextToken string returned on a previous page that you use to get the next page of results in a paginated response.",
            "Type": "string",
            "Required": false
        }
    },
    "list_conformance_pack_compliance_scores": {
        "Filters": {
            "Description": "Filters the results based on the ConformancePackComplianceScoresFilters .",
            "Type": "dict",
            "Required": false,
            "dict variables": {}
        },
        "SortOrder": {
            "Description": "Determines the order in which conformance pack compliance scores are sorted. Either in ascending or descending order.\nConformance packs with a compliance score of INSUFFICIENT_DATA will be first when sorting by ascending order and last when sorting by descending order.",
            "Type": "string",
            "Required": false
        },
        "SortBy": {
            "Description": "Sorts your conformance pack compliance scores in either ascending or descending order, depending on SortOrder .\nBy default, conformance pack compliance scores are sorted in ascending order by compliance score and alphabetically by name of the conformance pack if there is more than one conformance pack with the same compliance score.",
            "Type": "string",
            "Required": false
        },
        "Limit": {
            "Description": "The maximum number of conformance pack compliance scores returned on each page.",
            "Type": "integer",
            "Required": false
        },
        "NextToken": {
            "Description": "The nextToken string in a prior request that you can use to get the paginated response for next set of conformance pack compliance scores.",
            "Type": "string",
            "Required": false
        }
    },
    "list_discovered_resources": {
        "resourceType": {
            "Description": "The type of resources that you want Config to list in the response.",
            "Type": "string",
            "Required": true
        },
        "resourceIds": {
            "Description": "The IDs of only those resources that you want Config to list in the response. If you do not specify this parameter, Config lists all resources of the specified type that it has discovered.",
            "Type": "list",
            "Required": false,
            "list variables": {}
        },
        "resourceName": {
            "Description": "The custom name of only those resources that you want Config to list in the response. If you do not specify this parameter, Config lists all resources of the specified type that it has discovered.",
            "Type": "string",
            "Required": false
        },
        "limit": {
            "Description": "The maximum number of resource identifiers returned on each page. The default is 100. You cannot specify a number greater than 100. If you specify 0, Config uses the default.",
            "Type": "integer",
            "Required": false
        },
        "includeDeletedResources": {
            "Description": "Specifies whether Config includes deleted resources in the results. By default, deleted resources are not included.",
            "Type": "boolean",
            "Required": false
        },
        "nextToken": {
            "Description": "The nextToken string returned on a previous page that you use to get the next page of results in a paginated response.",
            "Type": "string",
            "Required": false
        }
    },
    "list_stored_queries": {
        "NextToken": {
            "Description": "The nextToken string returned in a previous request that you use to request the next page of results in a paginated response.",
            "Type": "string",
            "Required": false
        },
        "MaxResults": {
            "Description": "The maximum number of results to be returned with a single call.",
            "Type": "integer",
            "Required": false
        }
    },
    "list_tags_for_resource": {
        "ResourceArn": {
            "Description": "The Amazon Resource Name (ARN) that identifies the resource for which to list the tags. Currently, the supported resources are ConfigRule, ConfigurationAggregator and AggregatorAuthorization .",
            "Type": "string",
            "Required": true
        },
        "Limit": {
            "Description": "The maximum number of tags returned on each page. The limit maximum is 50. You cannot specify a number greater than 50. If you specify 0, Config uses the default.",
            "Type": "integer",
            "Required": false
        },
        "NextToken": {
            "Description": "The nextToken string returned on a previous page that you use to get the next page of results in a paginated response.",
            "Type": "string",
            "Required": false
        }
    },
    "put_aggregation_authorization": {
        "AuthorizedAccountId": {
            "Description": "The 12-digit account ID of the account authorized to aggregate data.",
            "Type": "string",
            "Required": true
        },
        "AuthorizedAwsRegion": {
            "Description": "The region authorized to collect aggregated data.",
            "Type": "string",
            "Required": true
        },
        "Tags": {
            "Description": "An array of tag object.",
            "Type": "list",
            "Required": false,
            "list variables": {}
        }
    },
    "put_config_rule": {
        "ConfigRule": {
            "Description": "The rule that you want to add to your account.",
            "Type": "dict",
            "Required": true,
            "dict variables": {}
        },
        "Tags": {
            "Description": "An array of tag object.",
            "Type": "list",
            "Required": false,
            "list variables": {}
        }
    },
    "put_configuration_aggregator": {
        "ConfigurationAggregatorName": {
            "Description": "The name of the configuration aggregator.",
            "Type": "string",
            "Required": true
        },
        "AccountAggregationSources": {
            "Description": "A list of AccountAggregationSource object.",
            "Type": "list",
            "Required": false,
            "list variables": {}
        },
        "OrganizationAggregationSource": {
            "Description": "An OrganizationAggregationSource object.",
            "Type": "dict",
            "Required": false,
            "dict variables": {}
        },
        "Tags": {
            "Description": "An array of tag object.",
            "Type": "list",
            "Required": false,
            "list variables": {}
        }
    },
    "put_configuration_recorder": {
        "ConfigurationRecorder": {
            "Description": "The configuration recorder object that records each configuration change made to the resources.",
            "Type": "dict",
            "Required": true,
            "dict variables": {}
        }
    },
    "put_conformance_pack": {
        "ConformancePackName": {
            "Description": "The unique name of the conformance pack you want to deploy.",
            "Type": "string",
            "Required": true
        },
        "TemplateS3Uri": {
            "Description": "The location of the file containing the template body (s3://bucketname/prefix ). The uri must point to a conformance pack template (max size: 300 KB) that is located in an Amazon S3 bucket in the same region as the conformance pack.",
            "Type": "string",
            "Required": false
        },
        "TemplateBody": {
            "Description": "A string containing the full conformance pack template body. The structure containing the template body has a minimum length of 1 byte and a maximum length of 51,200 bytes.",
            "Type": "string",
            "Required": false
        },
        "DeliveryS3Bucket": {
            "Description": "The name of the Amazon S3 bucket where Config stores conformance pack templates.",
            "Type": "string",
            "Required": false
        },
        "DeliveryS3KeyPrefix": {
            "Description": "The prefix for the Amazon S3 bucket.",
            "Type": "string",
            "Required": false
        },
        "ConformancePackInputParameters": {
            "Description": "A list of ConformancePackInputParameter objects.",
            "Type": "list",
            "Required": false,
            "list variables": {}
        },
        "TemplateSSMDocumentDetails": {
            "Description": "An object of type TemplateSSMDocumentDetails, which contains the name or the Amazon Resource Name (ARN) of the Amazon Web Services Systems Manager document (SSM document) and the version of the SSM document that is used to create a conformance pack.",
            "Type": "dict",
            "Required": false,
            "dict variables": {}
        }
    },
    "put_delivery_channel": {
        "DeliveryChannel": {
            "Description": "The configuration delivery channel object that delivers the configuration information to an Amazon S3 bucket and to an Amazon SNS topic.",
            "Type": "dict",
            "Required": true,
            "dict variables": {}
        }
    },
    "put_evaluations": {
        "Evaluations": {
            "Description": "The assessments that the Lambda function performs. Each evaluation identifies an Amazon Web Services resource and indicates whether it complies with the Config rule that invokes the Lambda function.",
            "Type": "list",
            "Required": false,
            "list variables": {}
        },
        "ResultToken": {
            "Description": "An encrypted token that associates an evaluation with an Config rule. Identifies the rule and the event that triggered the evaluation.",
            "Type": "string",
            "Required": true
        },
        "TestMode": {
            "Description": "Use this parameter to specify a test run for PutEvaluations. You can verify whether your Lambda function will deliver evaluation results to Config. No updates occur to your existing evaluations, and evaluation results are not sent to Config.",
            "Type": "boolean",
            "Required": false
        }
    },
    "put_external_evaluation": {
        "ConfigRuleName": {
            "Description": "The name of the Config rule.",
            "Type": "string",
            "Required": true
        },
        "ExternalEvaluation": {
            "Description": "An ExternalEvaluation object that provides details about compliance.",
            "Type": "dict",
            "Required": true,
            "dict variables": {}
        }
    },
    "put_organization_config_rule": {
        "OrganizationConfigRuleName": {
            "Description": "The name that you assign to an organization Config rule.",
            "Type": "string",
            "Required": true
        },
        "OrganizationManagedRuleMetadata": {
            "Description": "An OrganizationManagedRuleMetadata object. This object specifies organization managed rule metadata such as resource type and ID of Amazon Web Services resource along with the rule identifier. It also provides the frequency with which you want Config to run evaluations for the rule if the trigger type is periodic.",
            "Type": "dict",
            "Required": false,
            "dict variables": {}
        },
        "OrganizationCustomRuleMetadata": {
            "Description": "An OrganizationCustomRuleMetadata object. This object specifies organization custom rule metadata such as resource type, resource ID of Amazon Web Services resource, Lambda function ARN, and organization trigger types that trigger Config to evaluate your Amazon Web Services resources against a rule. It also provides the frequency with which you want Config to run evaluations for the rule if the trigger type is periodic.",
            "Type": "dict",
            "Required": false,
            "dict variables": {}
        },
        "ExcludedAccounts": {
            "Description": "A comma-separated list of accounts that you want to exclude from an organization Config rule.",
            "Type": "list",
            "Required": false,
            "list variables": {}
        },
        "OrganizationCustomPolicyRuleMetadata": {
            "Description": "An OrganizationCustomPolicyRuleMetadata object. This object specifies metadata for your organization's Config Custom Policy rule. The metadata includes the runtime system in use, which accounts have debug logging enabled, and other custom rule metadata, such as resource type, resource ID of Amazon Web Services resource, and organization trigger types that initiate Config to evaluate Amazon Web Services resources against a rule.",
            "Type": "dict",
            "Required": false,
            "dict variables": {}
        }
    },
    "put_organization_conformance_pack": {
        "OrganizationConformancePackName": {
            "Description": "Name of the organization conformance pack you want to create.",
            "Type": "string",
            "Required": true
        },
        "TemplateS3Uri": {
            "Description": "Location of file containing the template body. The uri must point to the conformance pack template (max size: 300 KB).",
            "Type": "string",
            "Required": false
        },
        "TemplateBody": {
            "Description": "A string containing full conformance pack template body. Structure containing the template body with a minimum length of 1 byte and a maximum length of 51,200 bytes.",
            "Type": "string",
            "Required": false
        },
        "DeliveryS3Bucket": {
            "Description": "The name of the Amazon S3 bucket where Config stores conformance pack templates.",
            "Type": "string",
            "Required": false
        },
        "DeliveryS3KeyPrefix": {
            "Description": "The prefix for the Amazon S3 bucket.",
            "Type": "string",
            "Required": false
        },
        "ConformancePackInputParameters": {
            "Description": "A list of ConformancePackInputParameter objects.",
            "Type": "list",
            "Required": false,
            "list variables": {}
        },
        "ExcludedAccounts": {
            "Description": "A list of Amazon Web Services accounts to be excluded from an organization conformance pack while deploying a conformance pack.",
            "Type": "list",
            "Required": false,
            "list variables": {}
        }
    },
    "put_remediation_configurations": {
        "RemediationConfigurations": {
            "Description": "A list of remediation configuration objects.",
            "Type": "list",
            "Required": true,
            "list variables": {}
        }
    },
    "put_remediation_exceptions": {
        "ConfigRuleName": {
            "Description": "The name of the Config rule for which you want to create remediation exception.",
            "Type": "string",
            "Required": true
        },
        "ResourceKeys": {
            "Description": "An exception list of resource exception keys to be processed with the current request. Config adds exception for each resource key. For example, Config adds 3 exceptions for 3 resource keys.",
            "Type": "list",
            "Required": true,
            "list variables": {}
        },
        "Message": {
            "Description": "The message contains an explanation of the exception.",
            "Type": "string",
            "Required": false
        },
        "ExpirationTime": {
            "Description": "The exception is automatically deleted after the expiration date.",
            "Type": "datetime",
            "Required": false
        }
    },
    "put_resource_config": {
        "ResourceType": {
            "Description": "The type of the resource. The custom resource type must be registered with CloudFormation.",
            "Type": "string",
            "Required": true
        },
        "SchemaVersionId": {
            "Description": "Version of the schema registered for the ResourceType in CloudFormation.",
            "Type": "string",
            "Required": true
        },
        "ResourceId": {
            "Description": "Unique identifier of the resource.",
            "Type": "string",
            "Required": true
        },
        "ResourceName": {
            "Description": "Name of the resource.",
            "Type": "string",
            "Required": false
        },
        "Configuration": {
            "Description": "The configuration object of the resource in valid JSON format. It must match the schema registered with CloudFormation.",
            "Type": "string",
            "Required": true
        },
        "Tags": {
            "Description": "Tags associated with the resource.",
            "Type": "dict",
            "Required": false,
            "dict variables": {}
        }
    },
    "put_retention_configuration": {
        "RetentionPeriodInDays": {
            "Description": "Number of days Config stores your historical information.",
            "Type": "integer",
            "Required": true
        }
    },
    "put_stored_query": {
        "StoredQuery": {
            "Description": "A list of StoredQuery objects. The mandatory fields are QueryName and Expression .",
            "Type": "dict",
            "Required": true,
            "dict variables": {}
        },
        "Tags": {
            "Description": "A list of Tags object.",
            "Type": "list",
            "Required": false,
            "list variables": {}
        }
    },
    "select_aggregate_resource_config": {
        "Expression": {
            "Description": "The SQL query SELECT command.",
            "Type": "string",
            "Required": true
        },
        "ConfigurationAggregatorName": {
            "Description": "The name of the configuration aggregator.",
            "Type": "string",
            "Required": true
        },
        "Limit": {
            "Description": "The maximum number of query results returned on each page.",
            "Type": "integer",
            "Required": false
        },
        "MaxResults": {
            "Description": "The maximum number of query results returned on each page. Config also allows the Limit request parameter.",
            "Type": "integer",
            "Required": false
        },
        "NextToken": {
            "Description": "The nextToken string returned in a previous request that you use to request the next page of results in a paginated response.",
            "Type": "string",
            "Required": false
        }
    },
    "select_resource_config": {
        "Expression": {
            "Description": "The SQL query SELECT command.",
            "Type": "string",
            "Required": true
        },
        "Limit": {
            "Description": "The maximum number of query results returned on each page.",
            "Type": "integer",
            "Required": false
        },
        "NextToken": {
            "Description": "The nextToken string returned in a previous request that you use to request the next page of results in a paginated response.",
            "Type": "string",
            "Required": false
        }
    },
    "start_config_rules_evaluation": {
        "ConfigRuleNames": {
            "Description": "The list of names of Config rules that you want to run evaluations for.",
            "Type": "list",
            "Required": false,
            "list variables": {}
        }
    },
    "start_configuration_recorder": {
        "ConfigurationRecorderName": {
            "Description": "The name of the recorder object that records each configuration change made to the resources.",
            "Type": "string",
            "Required": true
        }
    },
    "start_remediation_execution": {
        "ConfigRuleName": {
            "Description": "The list of names of Config rules that you want to run remediation execution for.",
            "Type": "string",
            "Required": true
        },
        "ResourceKeys": {
            "Description": "A list of resource keys to be processed with the current request. Each element in the list consists of the resource type and resource ID.",
            "Type": "list",
            "Required": true,
            "list variables": {}
        }
    },
    "stop_configuration_recorder": {
        "ConfigurationRecorderName": {
            "Description": "The name of the recorder object that records each configuration change made to the resources.",
            "Type": "string",
            "Required": true
        }
    },
    "tag_resource": {
        "ResourceArn": {
            "Description": "The Amazon Resource Name (ARN) that identifies the resource for which to list the tags. Currently, the supported resources are ConfigRule, ConfigurationAggregator and AggregatorAuthorization .",
            "Type": "string",
            "Required": true
        },
        "Tags": {
            "Description": "An array of tag object.",
            "Type": "list",
            "Required": true,
            "list variables": {}
        }
    },
    "untag_resource": {
        "ResourceArn": {
            "Description": "The Amazon Resource Name (ARN) that identifies the resource for which to list the tags. Currently, the supported resources are ConfigRule, ConfigurationAggregator and AggregatorAuthorization .",
            "Type": "string",
            "Required": true
        },
        "TagKeys": {
            "Description": "The keys of the tags to be removed.",
            "Type": "list",
            "Required": true,
            "list variables": {}
        }
    },
    "paginate": {
        "Expression": {
            "Description": "The SQL query SELECT command.",
            "Type": "string",
            "Required": true
        },
        "PaginationConfig": {
            "Description": "A dictionary that provides parameters to control pagination.",
            "Type": "dict",
            "Required": false,
            "dict variables": {}
        }
    }
}