{
    "list_realtime_contact_analysis_segments": {
        "InstanceId": {
            "Description": "The identifier of the Amazon Connect instance.",
            "Type": "string",
            "Required": true
        },
        "ContactId": {
            "Description": "The identifier of the contact.",
            "Type": "string",
            "Required": true
        },
        "MaxResults": {
            "Description": "The maximimum number of results to return per page.",
            "Type": "integer",
            "Required": false
        },
        "NextToken": {
            "Description": "The token for the next set of results. Use the value returned in the previous response in the next request to retrieve the next set of results.",
            "Type": "string",
            "Required": false
        }
    }
}